chris_study_mcp_demo/__init__.py
chris_study_mcp_demo-0.1.0.dist-info/WHEEL
chris_study_mcp_demo-0.1.0.dist-info/entry_points.txt
chris_study_mcp_demo-0.1.0.dist-info/METADATA
chris_study_mcp_demo-0.1.0.dist-info/RECORD
