Metadata-Version: 2.3
Name: chris-study-mcp-demo
Version: 0.1.0
Summary: Add your description here
Author: chris
Author-email: chris <246267555@qq.com>
Requires-Dist: mcp[cli]>=1.13.1
Requires-Python: >=3.12.0
